[{"id":"hill-tLjvhYqf","date":"2018-07-08T01:49:13.323Z","mediaFilename":"hill-tLjvhYqf.png","altText":"A hill.","caption":"","postedToGit":true,"htmlFragment":"<li class=\"pane\">\n  <div class=\"time-stamp entry-meta\">\n    <a href=\"hill-tLjvhYqf.html\">\n      <time datetime=\"2018-07-08T01:49:13.323Z\">2018-7-7 21:49:13</time>\n    </a>\n  </div><img src=\"media/hill-tLjvhYqf.png\" alt=\"A hill.\"></video><div class=\"media-caption entry-meta\"></div></li>","postedSingleVideoPage":true},{"id":"hill-dxlrGnbH","date":"2018-07-08T04:49:16.357Z","mediaFilename":"hill-dxlrGnbH.png","altText":"A hill.","caption":"","postedToGit":true,"htmlFragment":"<li class=\"pane\">\n  <div class=\"time-stamp entry-meta\">\n    <a href=\"hill-dxlrGnbH.html\">\n      <time datetime=\"2018-07-08T04:49:16.357Z\">2018-7-8 00:49:16</time>\n    </a>\n  </div><img src=\"media/hill-dxlrGnbH.png\" alt=\"A hill.\"></video><div class=\"media-caption entry-meta\"></div></li>","postedSingleVideoPage":true},{"id":"hill-fNbaJUJY","date":"2018-07-08T07:49:10.406Z","mediaFilename":"hill-fNbaJUJY.png","altText":"A hill.","caption":"","postedToGit":true,"htmlFragment":"<li class=\"pane\">\n  <div class=\"time-stamp entry-meta\">\n    <a href=\"hill-fNbaJUJY.html\">\n      <time datetime=\"2018-07-08T07:49:10.406Z\">2018-7-8 03:49:10</time>\n    </a>\n  </div><img src=\"media/hill-fNbaJUJY.png\" alt=\"A hill.\"></video><div class=\"media-caption entry-meta\"></div></li>","postedSingleVideoPage":true},{"id":"hill-clXHYbZg","date":"2018-07-08T10:49:11.239Z","mediaFilename":"hill-clXHYbZg.png","altText":"A hill.","caption":"","postedToGit":true,"htmlFragment":"<li class=\"pane\">\n  <div class=\"time-stamp entry-meta\">\n    <a href=\"hill-clXHYbZg.html\">\n      <time datetime=\"2018-07-08T10:49:11.239Z\">2018-7-8 06:49:11</time>\n    </a>\n  </div><img src=\"media/hill-clXHYbZg.png\" alt=\"A hill.\"></video><div class=\"media-caption entry-meta\"></div></li>","postedSingleVideoPage":true},{"id":"hill-UKwLGOPW","date":"2018-07-08T13:49:10.268Z","mediaFilename":"hill-UKwLGOPW.png","altText":"A hill.","caption":"","postedToGit":true,"htmlFragment":"<li class=\"pane\">\n  <div class=\"time-stamp entry-meta\">\n    <a href=\"hill-UKwLGOPW.html\">\n      <time datetime=\"2018-07-08T13:49:10.268Z\">2018-7-8 09:49:10</time>\n    </a>\n  </div><img src=\"media/hill-UKwLGOPW.png\" alt=\"A hill.\"></video><div class=\"media-caption entry-meta\"></div></li>","postedSingleVideoPage":true},{"id":"hill-PDLFxlHd","date":"2018-07-08T16:49:15.114Z","mediaFilename":"hill-PDLFxlHd.png","altText":"A hill.","caption":"","postedToGit":true,"htmlFragment":"<li class=\"pane\">\n  <div class=\"time-stamp entry-meta\">\n    <a href=\"hill-PDLFxlHd.html\">\n      <time datetime=\"2018-07-08T16:49:15.114Z\">2018-7-8 12:49:15</time>\n    </a>\n  </div><img src=\"media/hill-PDLFxlHd.png\" alt=\"A hill.\"></video><div class=\"media-caption entry-meta\"></div></li>","postedSingleVideoPage":true},{"id":"hill-bQVkwbjb","date":"2018-07-08T19:49:12.927Z","mediaFilename":"hill-bQVkwbjb.png","altText":"A hill.","caption":"","postedToGit":true,"htmlFragment":"<li class=\"pane\">\n  <div class=\"time-stamp entry-meta\">\n    <a href=\"hill-bQVkwbjb.html\">\n      <time datetime=\"2018-07-08T19:49:12.927Z\">2018-7-8 15:49:12</time>\n    </a>\n  </div><img src=\"media/hill-bQVkwbjb.png\" alt=\"A hill.\"></video><div class=\"media-caption entry-meta\"></div></li>","postedSingleVideoPage":true},{"id":"hill-VzKDbELZ","date":"2018-07-08T22:49:12.892Z","mediaFilename":"hill-VzKDbELZ.png","altText":"A hill.","caption":"","postedToGit":true,"htmlFragment":"<li class=\"pane\">\n  <div class=\"time-stamp entry-meta\">\n    <a href=\"hill-VzKDbELZ.html\">\n      <time datetime=\"2018-07-08T22:49:12.892Z\">2018-7-8 18:49:12</time>\n    </a>\n  </div><img src=\"media/hill-VzKDbELZ.png\" alt=\"A hill.\"></video><div class=\"media-caption entry-meta\"></div></li>","postedSingleVideoPage":true},{"id":"hill-QWzgQSkT","date":"2018-07-09T01:49:12.552Z","mediaFilename":"hill-QWzgQSkT.png","altText":"A hill.","caption":"","postedToGit":true,"htmlFragment":"<li class=\"pane\">\n  <div class=\"time-stamp entry-meta\">\n    <a href=\"hill-QWzgQSkT.html\">\n      <time datetime=\"2018-07-09T01:49:12.552Z\">2018-7-8 21:49:12</time>\n    </a>\n  </div><img src=\"media/hill-QWzgQSkT.png\" alt=\"A hill.\"></video><div class=\"media-caption entry-meta\"></div></li>","postedSingleVideoPage":true},{"id":"hill-mkPNUwHs","date":"2018-07-09T04:49:10.558Z","mediaFilename":"hill-mkPNUwHs.png","altText":"A hill.","caption":"","postedToGit":true,"htmlFragment":"<li class=\"pane\">\n  <div class=\"time-stamp entry-meta\">\n    <a href=\"hill-mkPNUwHs.html\">\n      <time datetime=\"2018-07-09T04:49:10.558Z\">2018-7-9 00:49:10</time>\n    </a>\n  </div><img src=\"media/hill-mkPNUwHs.png\" alt=\"A hill.\"></video><div class=\"media-caption entry-meta\"></div></li>","postedSingleVideoPage":true}]