[{"id":"hill-caIVQFIa","date":"2018-06-03T10:49:13.522Z","mediaFilename":"hill-caIVQFIa.png","altText":"A hill.","caption":"","postedToGit":true,"htmlFragment":"<li class=\"pane\">\n  <div class=\"time-stamp entry-meta\">\n    <a href=\"hill-caIVQFIa.html\">\n      <time datetime=\"2018-06-03T10:49:13.522Z\">2018-6-3 06:49:13</time>\n    </a>\n  </div><img src=\"media/hill-caIVQFIa.png\" alt=\"A hill.\"></video><div class=\"media-caption entry-meta\"></div></li>","postedSingleVideoPage":true},{"id":"hill-yBcLpAcx","date":"2018-06-03T13:49:12.675Z","mediaFilename":"hill-yBcLpAcx.png","altText":"A hill.","caption":"","postedToGit":true,"htmlFragment":"<li class=\"pane\">\n  <div class=\"time-stamp entry-meta\">\n    <a href=\"hill-yBcLpAcx.html\">\n      <time datetime=\"2018-06-03T13:49:12.675Z\">2018-6-3 09:49:12</time>\n    </a>\n  </div><img src=\"media/hill-yBcLpAcx.png\" alt=\"A hill.\"></video><div class=\"media-caption entry-meta\"></div></li>","postedSingleVideoPage":true},{"id":"hill-uyJFbujK","date":"2018-06-03T16:49:13.264Z","mediaFilename":"hill-uyJFbujK.png","altText":"A hill.","caption":"","postedToGit":true,"htmlFragment":"<li class=\"pane\">\n  <div class=\"time-stamp entry-meta\">\n    <a href=\"hill-uyJFbujK.html\">\n      <time datetime=\"2018-06-03T16:49:13.264Z\">2018-6-3 12:49:13</time>\n    </a>\n  </div><img src=\"media/hill-uyJFbujK.png\" alt=\"A hill.\"></video><div class=\"media-caption entry-meta\"></div></li>","postedSingleVideoPage":true}]