[{"id":"hill-YxYClyBL","date":"2018-06-11T10:49:15.076Z","mediaFilename":"hill-YxYClyBL.png","altText":"A hill.","caption":"","postedToGit":true,"htmlFragment":"<li class=\"pane\">\n  <div class=\"time-stamp entry-meta\">\n    <a href=\"hill-YxYClyBL.html\">\n      <time datetime=\"2018-06-11T10:49:15.076Z\">2018-6-11 06:49:15</time>\n    </a>\n  </div><img src=\"media/hill-YxYClyBL.png\" alt=\"A hill.\"></video><div class=\"media-caption entry-meta\"></div></li>","postedSingleVideoPage":true},{"id":"hill-tHDlxgtW","date":"2018-06-11T16:49:12.859Z","mediaFilename":"hill-tHDlxgtW.png","altText":"A hill.","caption":"","postedToGit":true,"htmlFragment":"<li class=\"pane\">\n  <div class=\"time-stamp entry-meta\">\n    <a href=\"hill-tHDlxgtW.html\">\n      <time datetime=\"2018-06-11T16:49:12.859Z\">2018-6-11 12:49:12</time>\n    </a>\n  </div><img src=\"media/hill-tHDlxgtW.png\" alt=\"A hill.\"></video><div class=\"media-caption entry-meta\"></div></li>","postedSingleVideoPage":true},{"id":"hill-rrWUwQAr","date":"2018-06-11T19:49:15.822Z","mediaFilename":"hill-rrWUwQAr.png","altText":"A hill.","caption":"","postedToGit":true,"htmlFragment":"<li class=\"pane\">\n  <div class=\"time-stamp entry-meta\">\n    <a href=\"hill-rrWUwQAr.html\">\n      <time datetime=\"2018-06-11T19:49:15.822Z\">2018-6-11 15:49:15</time>\n    </a>\n  </div><img src=\"media/hill-rrWUwQAr.png\" alt=\"A hill.\"></video><div class=\"media-caption entry-meta\"></div></li>","postedSingleVideoPage":true},{"id":"hill-ToiRLZeE","date":"2018-06-11T22:49:10.524Z","mediaFilename":"hill-ToiRLZeE.png","altText":"A hill.","caption":"","postedToGit":true,"htmlFragment":"<li class=\"pane\">\n  <div class=\"time-stamp entry-meta\">\n    <a href=\"hill-ToiRLZeE.html\">\n      <time datetime=\"2018-06-11T22:49:10.524Z\">2018-6-11 18:49:10</time>\n    </a>\n  </div><img src=\"media/hill-ToiRLZeE.png\" alt=\"A hill.\"></video><div class=\"media-caption entry-meta\"></div></li>","postedSingleVideoPage":true},{"id":"hill-CIJfTlPV","date":"2018-06-12T01:49:13.395Z","mediaFilename":"hill-CIJfTlPV.png","altText":"A hill.","caption":"","postedToGit":true,"htmlFragment":"<li class=\"pane\">\n  <div class=\"time-stamp entry-meta\">\n    <a href=\"hill-CIJfTlPV.html\">\n      <time datetime=\"2018-06-12T01:49:13.395Z\">2018-6-11 21:49:13</time>\n    </a>\n  </div><img src=\"media/hill-CIJfTlPV.png\" alt=\"A hill.\"></video><div class=\"media-caption entry-meta\"></div></li>","postedSingleVideoPage":true},{"id":"hill-nqGdDBhS","date":"2018-06-12T04:49:12.663Z","mediaFilename":"hill-nqGdDBhS.png","altText":"A hill.","caption":"","postedToGit":true,"htmlFragment":"<li class=\"pane\">\n  <div class=\"time-stamp entry-meta\">\n    <a href=\"hill-nqGdDBhS.html\">\n      <time datetime=\"2018-06-12T04:49:12.663Z\">2018-6-12 00:49:12</time>\n    </a>\n  </div><img src=\"media/hill-nqGdDBhS.png\" alt=\"A hill.\"></video><div class=\"media-caption entry-meta\"></div></li>","postedSingleVideoPage":true},{"id":"hill-yJbIOmWg","date":"2018-06-12T07:49:13.500Z","mediaFilename":"hill-yJbIOmWg.png","altText":"A hill.","caption":"","postedToGit":true,"htmlFragment":"<li class=\"pane\">\n  <div class=\"time-stamp entry-meta\">\n    <a href=\"hill-yJbIOmWg.html\">\n      <time datetime=\"2018-06-12T07:49:13.500Z\">2018-6-12 03:49:13</time>\n    </a>\n  </div><img src=\"media/hill-yJbIOmWg.png\" alt=\"A hill.\"></video><div class=\"media-caption entry-meta\"></div></li>","postedSingleVideoPage":true},{"id":"hill-hwOKaFlK","date":"2018-06-12T10:49:12.878Z","mediaFilename":"hill-hwOKaFlK.png","altText":"A hill.","caption":"","postedToGit":true,"htmlFragment":"<li class=\"pane\">\n  <div class=\"time-stamp entry-meta\">\n    <a href=\"hill-hwOKaFlK.html\">\n      <time datetime=\"2018-06-12T10:49:12.878Z\">2018-6-12 06:49:12</time>\n    </a>\n  </div><img src=\"media/hill-hwOKaFlK.png\" alt=\"A hill.\"></video><div class=\"media-caption entry-meta\"></div></li>","postedSingleVideoPage":true},{"id":"hill-AhEriuEa","date":"2018-06-12T13:49:16.169Z","mediaFilename":"hill-AhEriuEa.png","altText":"A hill.","caption":"","postedToGit":true,"htmlFragment":"<li class=\"pane\">\n  <div class=\"time-stamp entry-meta\">\n    <a href=\"hill-AhEriuEa.html\">\n      <time datetime=\"2018-06-12T13:49:16.169Z\">2018-6-12 09:49:16</time>\n    </a>\n  </div><img src=\"media/hill-AhEriuEa.png\" alt=\"A hill.\"></video><div class=\"media-caption entry-meta\"></div></li>","postedSingleVideoPage":true}]